pytill/__init__.py
pytill/pytill.py
pytill-1.0.0.dist-info/METADATA
pytill-1.0.0.dist-info/RECORD
pytill-1.0.0.dist-info/WHEEL
pytill-1.0.0.dist-info/top_level.txt
