Metadata-Version: 2.1
Name: pytill
Version: 1.0.0
Summary: Python package for using Till Mobile
Home-page: https://github.com/manifoldco/pytill
Author: manifoldco
Author-email: dom@manifold.co
License: BSD license
Keywords: pytill
Platform: UNKNOWN
Classifier: Development Status :: 2 - Pre-Alpha
Classifier: Intended Audience :: Developers
Classifier: License :: OSI Approved :: BSD License
Classifier: Natural Language :: English
Classifier: Programming Language :: Python :: 2
Classifier: Programming Language :: Python :: 2.7
Classifier: Programming Language :: Python :: 3
Classifier: Programming Language :: Python :: 3.4
Classifier: Programming Language :: Python :: 3.5
Classifier: Programming Language :: Python :: 3.6
Classifier: Programming Language :: Python :: 3.7
